brass/__init__.py
brass/_brass.cpython-312-darwin.so
brass/cli/analyze_runs.py
brass/histNd.py
brass/meta/meta.py
brass/scan/__init__.py
brass/scan/commands.txt
brass/scan/get_cmds.py
brass/scan/scan.py
brass/scan/template.py
pybrass-0.1.0.dist-info/METADATA
pybrass-0.1.0.dist-info/WHEEL
pybrass-0.1.0.dist-info/entry_points.txt
pybrass-0.1.0.dist-info/licenses/LICENSE
pybrass-0.1.0.dist-info/RECORD
