Metadata-Version: 2.2
Name: pybrass
Version: 0.1.0
Summary: Binary Reader and Analysis Suite Software
Keywords: binary,reader,physics,heavy-ion,SMASH,pybind11
Author-Email: "Carl B. Rosenkvist" <rosenkvist@itp.uni-frankfurt.de>
License: MIT License
Classifier: Programming Language :: Python :: 3
Classifier: Programming Language :: Python :: 3 :: Only
Classifier: Programming Language :: C++
Classifier: License :: OSI Approved :: MIT License
Classifier: Operating System :: POSIX :: Linux
Classifier: Operating System :: MacOS
Classifier: Intended Audience :: Science/Research
Classifier: Topic :: Scientific/Engineering :: Physics
Project-URL: Homepage, https://github.com/Carl-Rosenkvist/brass
Project-URL: Source, https://github.com/Carl-Rosenkvist/brass
Project-URL: Issues, https://github.com/Carl-Rosenkvist/brass/issues
Requires-Python: >=3.8
Requires-Dist: numpy>=2.1.3
Requires-Dist: pyyaml>=6.0.2
Provides-Extra: dev
Requires-Dist: ruff; extra == "dev"
Requires-Dist: mypy; extra == "dev"
Requires-Dist: pytest; extra == "dev"
Requires-Dist: build; extra == "dev"
Requires-Dist: twine; extra == "dev"
